Find_book/Findyou_book.py
Find_book/__init__.py
Find_book/books.csv
fndy_bks/Findyou_book.py
fndy_bks/__init__.py
fndy_bks/books.csv
fndy_bks-1.0.1.dist-info/METADATA
fndy_bks-1.0.1.dist-info/WHEEL
fndy_bks-1.0.1.dist-info/top_level.txt
fndy_bks-1.0.1.dist-info/RECORD
